{"version":"1.020","provides":{"Template::Alloy::Stream":{"file":"lib/Template/Alloy/Stream.pm"},"Template::Alloy::TT":{"file":"lib/Template/Alloy/TT.pm"},"Template::Alloy::Exception":{"file":"lib/Template/Alloy/Exception.pm"},"Template::Alloy::Compile":{"file":"lib/Template/Alloy/Compile.pm"},"Template::Alloy::HTE":{"file":"lib/Template/Alloy/HTE.pm"},"Template::Alloy":{"version":"1.020","file":"lib/Template/Alloy.pm"},"Template::Alloy::EvalPerlHandle":{"file":"lib/Template/Alloy/Play.pm"},"Template::Alloy::Velocity":{"file":"lib/Template/Alloy/Velocity.pm"},"Template::Alloy::Iterator":{"file":"lib/Template/Alloy/Iterator.pm"},"Template::Alloy::Parse":{"file":"lib/Template/Alloy/Parse.pm"},"Template::Alloy::Perl":{"file":"lib/Template/Alloy/Compile.pm"},"Template::Alloy::_ContextStash":{"file":"lib/Template/Alloy/Context.pm"},"Template::Alloy::Play":{"file":"lib/Template/Alloy/Play.pm"},"Template::Alloy::Operator":{"file":"lib/Template/Alloy/Operator.pm"},"Template::Alloy::Context":{"file":"lib/Template/Alloy/Context.pm"},"Template::Alloy::VMethod":{"file":"lib/Template/Alloy/VMethod.pm"},"Template::Alloy::Tmpl":{"file":"lib/Template/Alloy/Tmpl.pm"}},"target":"Template::Alloy","name":"Template::Alloy","pathname":"R/RH/RHANDOM/Template-Alloy-1.020.tar.gz","dist":"Template-Alloy-1.020"}